sentry_options/__init__.py
sentry_options/sentry_options.abi3.so
sentry_options-0.0.9.dist-info/METADATA
sentry_options-0.0.9.dist-info/WHEEL
sentry_options.libs/libgcc_s-f685abf1.so.1
sentry_options-0.0.9.dist-info/RECORD
